{
	"format_version": "1.12.0",
	"minecraft:geometry": [
		{
			"description": {
				"identifier": "geometry.unknown",
				"texture_width": 128,
				"texture_height": 128,
				"visible_bounds_width": 3,
				"visible_bounds_height": 3.5,
				"visible_bounds_offset": [0, 1.25, 0]
			},
			"bones": [
				{
					"name": "TARDIF",
					"pivot": [0, 0, 0],
					"cubes": [
						{"origin": [-11.5, 0, -1.5], "size": [3, 38, 3], "pivot": [-0.5, 15, 9.5], "rotation": [0, -90, 0], "uv": [54, 78]},
						{"origin": [8.5, 0, -1.5], "size": [3, 38, 3], "pivot": [0.5, 16, 9.5], "rotation": [0, 90, 0], "uv": [54, 78], "mirror": true},
						{"origin": [-11.5, 38, -1.5], "size": [3, 2, 3], "pivot": [-0.5, 17, 9.5], "rotation": [0, -90, 0], "uv": [0, 123]},
						{"origin": [8.5, 38, -1.5], "size": [3, 2, 3], "pivot": [0.5, 18, 9.5], "rotation": [0, 90, 0], "uv": [0, 123], "mirror": true},
						{"origin": [-9.5, 32, -2.5], "size": [19, 4, 5], "uv": [12, 119]},
						{"origin": [-9.5, 36, -2.5], "size": [19, 1, 2], "uv": [67, 90]}
					]
				},
				{
					"name": "doors",
					"parent": "TARDIF",
					"pivot": [0.5, 0, 0.5]
				},
				{
					"name": "RightDoor",
					"parent": "doors",
					"pivot": [7.5, 16, 1],
					"cubes": [
						{"origin": [-0.5, 0, -0.5], "size": [8, 32, 2], "inflate": -0.001, "uv": [1, 79]},
						{"origin": [3, 18, -0.6], "size": [2, 2, 0], "inflate": -0.001, "uv": [0, 0]},
						{"origin": [0.5, 16, -2.5], "size": [0, 4, 2], "uv": [0, 64]},
						{"origin": [0.5, 16, 1.5], "size": [0, 4, 2], "pivot": [0.5, 18, 2.5], "rotation": [0, 180, 0], "uv": [0, 64]}
					]
				},
				{
					"name": "window",
					"parent": "RightDoor",
					"pivot": [4, 23, -0.5],
					"cubes": [
						{"origin": [1.5, 23, -0.5], "size": [5, 6, 2], "inflate": -0.001, "uv": [6, 15]}
					]
				},
				{
					"name": "LeftDoor",
					"parent": "doors",
					"pivot": [-7.5, 16, 1],
					"cubes": [
						{"origin": [-7.5, 0, -0.5], "size": [7, 32, 2], "inflate": -0.001, "uv": [23, 79]}
					]
				},
				{
					"name": "phone",
					"parent": "LeftDoor",
					"pivot": [-6.5, 19, -0.25],
					"cubes": [
						{"origin": [-6.5, 16, -0.5], "size": [5, 6, 2], "uv": [0, 54]},
						{"origin": [-6.5, 19, 1.5], "size": [2, 0, 1], "inflate": -0.001, "uv": [14, 6]},
						{"origin": [-2, 17, -1.5], "size": [0, 4, 1], "uv": [1, 65]}
					]
				},
				{
					"name": "phone2",
					"parent": "phone",
					"pivot": [-5.5, 19, 2.33333],
					"cubes": [
						{"origin": [-6.5, 19.5, 1.3], "size": [2, 2, 1], "inflate": -0.002, "uv": [0, 13]},
						{"origin": [-6.5, 16.5, 1.8], "size": [2, 5, 1], "uv": [8, 6]},
						{"origin": [-6.5, 16.5, 1.3], "size": [2, 2, 1], "inflate": -0.002, "uv": [0, 13]}
					]
				},
				{
					"name": "button 1",
					"parent": "phone",
					"pivot": [-3, 20.5, 3],
					"cubes": [
						{"origin": [-4, 19.5, 1.5], "size": [2, 2, 1], "inflate": -0.001, "pivot": [-3, 20.5, 3], "rotation": [0, 0, -45], "uv": [8, 12]}
					]
				},
				{
					"name": "button2",
					"parent": "phone",
					"pivot": [-3, 17.5, 3],
					"cubes": [
						{"origin": [-4, 16.5, 1.5], "size": [2, 2, 1], "inflate": -0.001, "pivot": [-3, 17.5, 3], "rotation": [0, 0, -45], "uv": [8, 12]}
					]
				},
				{
					"name": "window2",
					"parent": "LeftDoor",
					"pivot": [-4, 23, -0.5],
					"cubes": [
						{"origin": [-6.5, 23, -0.5], "size": [5, 6, 2], "inflate": -0.001, "uv": [6, 15], "mirror": true}
					]
				},
				{
					"name": "lamp lid",
					"parent": "TARDIF",
					"pivot": [2.5, 44, 9]
				},
				{
					"name": "window3",
					"parent": "TARDIF",
					"pivot": [4, 23, 18.5]
				},
				{
					"name": "window4",
					"parent": "TARDIF",
					"pivot": [-4, 23, 18.5]
				},
				{
					"name": "window5",
					"parent": "TARDIF",
					"pivot": [-9.5, 23, 5],
					"rotation": [0, -90, 0]
				},
				{
					"name": "window6",
					"parent": "TARDIF",
					"pivot": [-9.5, 23, 13],
					"rotation": [0, 90, 0]
				},
				{
					"name": "window7",
					"parent": "TARDIF",
					"pivot": [9.5, 23, 13],
					"rotation": [0, -90, 0]
				},
				{
					"name": "window8",
					"parent": "TARDIF",
					"pivot": [9.5, 23, 5],
					"rotation": [0, 90, 0]
				}
			]
		}
	]
}